f1_helper/__init__.py
f1_helper/main.py
f1_helper-0.1.0.dist-info/METADATA
f1_helper-0.1.0.dist-info/WHEEL
f1_helper-0.1.0.dist-info/entry_points.txt
f1_helper-0.1.0.dist-info/top_level.txt
f1_helper-0.1.0.dist-info/RECORD
