Metadata-Version: 2.4
Name: f1-helper
Version: 0.1.0
Summary: CLI tool to check F1 driver and constructor championship scenarios
Author-email: Saur Deshmukh <saur90044@gmail.com>
Keywords: F1,Formula 1,motorsport,CLI,championship,calculator
Classifier: Intended Audience :: End Users/Desktop
Classifier: Programming Language :: Python :: 3
Classifier: Programming Language :: Python :: 3.9
Classifier: Programming Language :: Python :: 3.10
Classifier: Topic :: Utilities
Requires-Python: >=3.9
Requires-Dist: fastf1>=2.5.0
Requires-Dist: tabulate>=0.9.0
